COPYRIGHT
LICENSE
MANIFEST.in
README
setup.py
test.py
bin/ns.conf
bin/pycom-nameserver
docs/Makefile
docs/apiref.rst
docs/conf.py
docs/config.rst
docs/extend.rst
docs/history.rst
docs/index.rst
docs/install.rst
docs/proto.rst
docs/status.rst
docs/theme/layout.html
docs/theme/theme.conf
pycom/__init__.py
pycom/__main__.py
pycom/base.py
pycom/constants.py
pycom/exceptions.py
pycom/helpers.py
pycom/interfaces.py
pycom/launcher.py
pycom/nsclient.py
pycom/utils.py
pycom.egg-info/PKG-INFO
pycom.egg-info/SOURCES.txt
pycom.egg-info/dependency_links.txt
pycom.egg-info/not-zip-safe
pycom.egg-info/requires.txt
pycom.egg-info/top_level.txt
pycom/apps/__init__.py
pycom/apps/demo.py
pycom/apps/nameserver.py
pycom/ext/__init__.py
pycom/test/__init__.py
pycom/test/test_apps_demo.py
pycom/test/test_apps_nameserver.py
pycom/test/test_base.py
pycom/test/test_interfaces.py
pycom/test/test_launcher.py
pycom/test/test_nsclient.py
pycom/test/test_utils.py
pycom/test/test_zerojson_call.py
pycom/test/test_zerojson_client.py
pycom/test/test_zerojson_common.py
pycom/test/utils.py
pycom/zerojson/__init__.py
pycom/zerojson/call.py
pycom/zerojson/client.py
pycom/zerojson/common.py
pycom/zerojson/prepare.py
pycom/zerojson/server.py