Metadata-Version: 1.1
Name: pycom
Version: 0.4.1
Summary: Distributed component model for Python.
Home-page: http://www.pycom.org
Author: Dmitry 'Divius' Tantsur
Author-email: divius.inside@gmail.com
License: BSD
Download-URL: http://pypi.python.org/pypi/pycom
Platform: UNKNOWN
Classifier: Development Status :: 4 - Beta
Classifier: Operating System :: POSIX
Classifier: Programming Language :: Python
Classifier: Programming Language :: Python :: 2
Classifier: Programming Language :: Python :: 2.6
Classifier: Programming Language :: Python :: 2.7
Classifier: Programming Language :: Python :: 3
Classifier: Programming Language :: Python :: 3.2
Classifier: Intended Audience :: Developers
Classifier: Intended Audience :: Information Technology
Classifier: Topic :: Software Development :: Libraries :: Application Frameworks
Classifier: Topic :: Software Development :: Libraries :: Python Modules
Classifier: Topic :: Software Development :: Object Brokering
Classifier: Topic :: System :: Distributed Computing
Classifier: Topic :: System :: Networking
Classifier: License :: OSI Approved :: BSD License
Requires: pyzmq (>=2.1.11)
Requires: six
